xml_thunder/__init__.py
xml_thunder/core.py
xml_thunder-0.1.0.dist-info/LICENSE
xml_thunder-0.1.0.dist-info/METADATA
xml_thunder-0.1.0.dist-info/WHEEL
xml_thunder-0.1.0.dist-info/top_level.txt
xml_thunder-0.1.0.dist-info/RECORD
